ingot/__init__.py
ingot/app.py
ingot/display.py
ingot/layouts.py
ingot/py.typed
ingot/toolbar.py
ingot/workspace.py
ingot/actions/__init__.py
ingot/actions/manager.py
ingot/scene/__init__.py
ingot/scene/drawable.py
ingot/scene/py.typed
ingot/scene/view.py
ingot/theming/manager.py
ingot/views/base.py
ingot/views/canvas.py
ingot/workspaces/__init__.py
ingot/workspaces/canvas.py
qt_ingot-0.0.5.dist-info/METADATA
qt_ingot-0.0.5.dist-info/WHEEL
qt_ingot-0.0.5.dist-info/licenses/LICENSE
qt_ingot-0.0.5.dist-info/RECORD
