Metadata-Version: 2.4
Name: qt-ingot
Version: 0.0.5
Summary: A lightweight, themeable boilerplate for creating tab-based PyQt applications.
Project-URL: Homepage, https://github.com/Yrrrrrf/qt-ingot
Project-URL: Repository, https://github.com/Yrrrrrf/qt-ingot
Author-email: Fernando Bryan Reza Campos <fer.rezac@outlook.com>
License: MIT
License-File: LICENSE
Keywords: gui,pyqt,pyqt6,qt,scaffolding,template
Classifier: Development Status :: 2 - Pre-Alpha
Classifier: Intended Audience :: Developers
Classifier: License :: OSI Approved :: MIT License
Classifier: Operating System :: OS Independent
Classifier: Programming Language :: Python :: 3.12
Classifier: Topic :: Desktop Environment
Classifier: Topic :: Software Development :: Libraries :: Application Frameworks
Classifier: Topic :: Software Development :: User Interfaces
Classifier: Typing :: Typed
Requires-Python: >=3.12
Requires-Dist: libsass>=0.23.0
Requires-Dist: pyqt6>=6.9.1
Requires-Dist: rich>=14.2.0
Requires-Dist: rune-lib>=0.0.4
